pystrm/__init__.py
pystrm/kHandler/__init__.py
pystrm/kHandler/kAdminstrator.py
pystrm/kHandler/kConsumer.py
pystrm/kHandler/kProducer.py
pystrm/kHandler/kSchemaRegistry.py
pystrm/kHandler/kUtils.py
pystrm/main.py
pystrm/mainCalls/__init__.py
pystrm/mainCalls/yfUtils.py
pystrm/pyproject.toml
pystrm/stream/yfStream/__init__.py
pystrm/stream/yfStream/ticksStream.py
pystrm/utils/common/__init__.py
pystrm/utils/common/confs.py
pystrm/utils/common/constants.py
pystrm/utils/common/genUtils.py
pystrm/utils/common/marketUtils.py
pystrm/utils/logger/QueueListenerHandler.py
pystrm/utils/logger/__init__.py
pystrm/utils/logger/jsonLogging.py
pystrm/utils/logger/logDecor.py
pystrm/utils/logger/psgLogging.py
pystrm-0.1.23.dist-info/WHEEL
pystrm-0.1.23.dist-info/entry_points.txt
pystrm-0.1.23.dist-info/METADATA
pystrm-0.1.23.dist-info/RECORD
