Metadata-Version: 2.3
Name: pystrm
Version: 0.1.23
Summary: Python Stream module for api to kafka topic
Requires-Dist: attrs>=25.4.0
Requires-Dist: confluent-kafka~=2.6.0
Requires-Dist: fastavro>=1.10.0
Requires-Dist: jsonschema>=4.23.0
Requires-Dist: multiprocessing-logging>=0.3.4
Requires-Dist: pandas-market-calendars>=5.2.2
Requires-Dist: psycopg2-binary>=2.9.10
Requires-Dist: pytest>=9.0.2
Requires-Dist: pyyaml>=6.0.2
Requires-Dist: xxhash>=3.5.0
Requires-Dist: yfinance>=0.2.65
Requires-Python: >=3.11, <3.12
